musicscan/__init__.py
musicscan/data/__init__.py
musicscan/data/analyzer.py
musicscan/data/artist.py
musicscan/data/cd.py
musicscan/data/flagcodes.py
musicscan/data/flags.py
musicscan/data/library.py
musicscan/data/stringtools.py
musicscan/data/titletools.py
musicscan/data/track.py
musicscan/fileops/__init__.py
musicscan/fileops/filenames.py
musicscan/fileops/scanner.py
musicscan/fileops/xmlwriter.py
musicscan/generic/__init__.py
musicscan/generic/stats.py
musicscan/tools/__init__.py
musicscan/tools/id3scan.py
musicscan/xml/__init__.py
musicscan/xml/builder.py
musicscan-0.2.3.dist-info/licenses/LICENSE
musicscan-0.2.3.dist-info/METADATA
musicscan-0.2.3.dist-info/WHEEL
musicscan-0.2.3.dist-info/entry_points.txt
musicscan-0.2.3.dist-info/top_level.txt
musicscan-0.2.3.dist-info/RECORD
