Metadata-Version: 2.4
Name: musicscan
Version: 0.2.3
Summary: Package for converting music metadata to XML
Author-email: Chris J <cjcodeproj@fastmail.com>
License-Expression: MIT
Project-URL: homepage, https://github.com/cjcodeproj/musicscan
Project-URL: bug tracker, https://github.com/cjcodeproj/musicscan/issues
Project-URL: repository, https://github.com/cjcodeproj/musicscan
Project-URL: changelog, https://github.com/cjcodeproj/musicscan/blob/main/CHANGELOG.md
Keywords: xml,music,cds,metadata,id3,mp3,m4a,wav
Classifier: Development Status :: 4 - Beta
Classifier: Environment :: Console
Classifier: Intended Audience :: Developers
Classifier: Operating System :: OS Independent
Classifier: Programming Language :: Python :: 3
Classifier: Programming Language :: Python :: 3.9
Classifier: Topic :: Text Processing :: Markup :: XML
Classifier: Topic :: Multimedia
Classifier: Topic :: Multimedia :: Sound/Audio
Classifier: Topic :: Multimedia :: Sound/Audio :: Analysis
Classifier: Typing :: Typed
Requires-Python: >=3.9
License-File: LICENSE
Requires-Dist: tinytag
Dynamic: license-file
